Workbook

Sheet Overview
A1: COMET — Annual Media Plan · FY 2027-28
A2: Earn a movement, not an ad. Turn Rs 29 Cr into Rs 100 Cr.
A3: Deploy Rs 35 Cr of a Rs 50 Cr war chest | reserve Rs 15 Cr | blended ROAS ~2.8x | north star: share of search
A5: INVESTMENT SUMMARY
A6: Investment | B6: Amount (Rs Cr) | C6: % deploy | F6: Why
A7: Performance / conversion | B7: 20 | C7: 0.57 | F7: Volume engine; harvests Oct-Jan demand on high-intent channels
A8: Brand amplification | B8: 6 | C8: 0.17 | F8: Fuels the 6-week burst: YouTube, Meta, OTT, anamorphic OOH
A9: Productions (earned engine) | B9: 9 | C9: 0.26 | F9: Report, film, parties, OOH, sessions, chip, influencers
A10: Total deploy | B10: =SUM(B7:B9) -> 35 | C10: 1 | F10: Plus Rs 15 Cr in reserve
A13: OUTCOME MODEL (live; honest paid vs brand-driven split)
A14: Metric | B14: Value | F14: Formula / note
A15: Site visits (paid CPC clicks) | B15: =Assumptions!B14/Assumptions!B7 -> 8666666.7 | F15: CPC-channel spend / blended CPC
A16: Paid orders | B16: =B15*Assumptions!B6 -> 130000 | F16: visits x conversion rate
A17: Paid-channel revenue (Rs) | B17: =B16*Assumptions!B5 -> 585000000 | F17: orders x AOV (~Rs 58 Cr from paid)
A18: Blended ROAS (base Rs 85 Cr) | B18: =850000000/Assumptions!B9 -> 2.4285714 | F18: base revenue / deploy
A19: Blended ROAS (stretch Rs 100 Cr) | B19: =1000000000/Assumptions!B9 -> 2.8571429 | F19: stretch revenue / deploy
A20: Fully-loaded CAC at base (Rs) | B20: =Assumptions!B9/(850000000/Assumptions!B5) -> 1852.9412 | F20: deploy / base orders
A22: Paid CPC channels deliver ~Rs 58 Cr; marketplace, organic, direct and repeat (the brand-driven half) bridge to the Rs 85 Cr base / Rs 100 Cr stretch, which is why ~40% brand spend earns its place. Each quarter sheet = digital + influencer + OOH + (Q4) store-visit; the Budget sheet is the master Rs 35 Cr reconciliation.

Sheet Assumptions
A1: Assumptions & benchmarks
A2: Inputs are given or sourced. Quarter formulas reference these cells, so changing a value updates the maths.
A4: Input | B4: Value | C4: Source / rationale
A5: Average order value (AOV, Rs) [B5] | B5: 4500 | C5: Real Comet pricing Rs 4,299-5,999 (wearcomet.com)
A6: Site conversion rate [B6] | B6: 0.015 | C6: India D2C footwear benchmark
A7: Blended performance CPC (Rs) [B7] | B7: 15 | C7: Blend of Search Rs 25 + Meta Rs 12 + marketplace
A8: Performance spend (Rs) [B8] | B8: 200000000 | C8: Rs 20 Cr of the Rs 35 Cr deploy
A9: Total deploy (Rs) [B9] | B9: 350000000 | C9: Rs 35 Cr of the Rs 50 Cr war chest
A10: Reserve (Rs) [B10] | B10: 150000000 | C10: Held as fuel-on-success
A11: GST [B11] | B11: 0.18 | C11: Net media; gross = net + 18% GST
A12: FY25 revenue (Rs) [B12] | B12: 291000000 | C12: Audited; up ~4x from FY24
A13: Pairs sold now [B13] | B13: 65000 | C13: Revenue / AOV
A14: Paid-click spend, CPC channels (Rs) [B14] | B14: 130000000 | C14: Sum of Search + Meta + retargeting + IG-consideration lines; drives online orders
A15: Media benchmarks (used by quarter formulas)
A16: Display / social CTR [B16] | B16: 0.008 | C16: Reels/banner click-through
A17: Search / CPC landing CTR [B17] | B17: 0.012 | C17: Back out impressions from clicks
A18: Video VTR [B18] | B18: 0.3 | C18: View-through rate (YouTube ~31.8%)
A19: Marketplace CTR [B19] | B19: 0.01 | C19: Myntra / PLA
A20: Store-visit footfall rate [B20] | B20: 0.04 | C20: Clicks that become store visits
A21: Target audience size [B21] | B21: 80000000 | C21: Reachable urban Gen Z (for SOI %)
A23: Platform rate card (sourced, India 2025-26)
A24: Platform / buy type | B24: Rate | C24: Source
A25: YouTube CPV (skippable) | B25: Rs 1.0 | C25: TheDMSchool / OwlClaw: India CPV Rs 0.5-3
A26: Meta / IG CPM | B26: Rs 80 | C26: Superads / productgrowth.in: India Rs 50-90
A27: Meta / IG CPC | B27: Rs 12 | C27: Superads: India Rs 2-25 (IG Rs 6-55)
A28: Google Display CPM | B28: Rs 50 | C28: India GDN Rs 30-80
A29: Google Search CPC (fashion) | B29: Rs 25 | C29: OwlClaw / ReuAds: e-comm Rs 15-80, avg Rs 24
A30: OTT (JioHotstar) CPM | B30: Rs 250 | C30: Industry estimate Rs 180-300
A31: Marketplace (Myntra) CPM | B31: Rs 150 | C31: Directional
A32: Influencer per reel (by tier) | B32: see table | C32: Mid Rs 1-4L; micro Rs 15-75k; nano Rs 2-10k; macro far higher - the.rebel.kid ~Rs 25-30L, Rannvijay ~Rs 15-20L; so lean mid+micro+nano (Idiotic Media / Exchange4media)

Sheet Q1
A1: COMET media plan · Q1 (Apr-Jun)
K3: Estimated
A4: Platform | B4: Campaign objective | C4: AIDA | D4: Type | E4: Device | F4: Targeting | G4: Geo | H4: Ad format | I4: Buy type | J4: Net rate (Rs) | K4: Audience / search vol | L4: Reach % (SOI) | M4: Est. reach | N4: Avg freq | O4: Est. impressions | P4: Est. clicks | Q4: Est. CTR | R4: Est. views | S4: Est. VTR | T4: Net cost (Rs Cr) | U4: Rationale
A5: YouTube | B5: Awareness | C5: See | D5: Branding | E5: Mobile | F5: 18-30 M/F, interest + LAL | G5: Top metros + Tier-2 | H5: Skippable in-stream | I5: CPV | J5: 1 | K5: =Assumptions!$B$21 -> 80000000 | L5: =M5/K5 -> 0.069444444 | M5: =O5/N5 -> 5555555.6 | N5: 3 | O5: =R5/Assumptions!$B$18 -> 16666667 | P5: =O5*Assumptions!$B$16 -> 133333.33 | Q5: =P5/O5 -> 0.008 | R5: =T5*10000000/J5 -> 5000000 | S5: =R5/O5 -> 0.3 | T5: 0.5 | U5: Seed awareness pre-burst
A6: Meta / Instagram | B6: Awareness | C6: See | D6: Branding | E6: Mobile | F6: 18-30 M/F, interest + LAL | G6: Top metros + Tier-2 | H6: Reels / Stories video | I6: CPM | J6: 80 | K6: =Assumptions!$B$21 -> 80000000 | L6: =M6/K6 -> 0.15625 | M6: =O6/N6 -> 12500000 | N6: 3 | O6: =T6*10000000/J6*1000 -> 37500000 | P6: =O6*Assumptions!$B$16 -> 300000 | Q6: =P6/O6 -> 0.008 | T6: 0.3 | U6: Build brand presence
A7: Google Display | B7: Awareness | C7: See | D7: Branding | E7: Mobile | F7: 18-30 M/F, interest + LAL | G7: Top metros + Tier-2 | H7: Responsive display | I7: CPM | J7: 50 | K7: =Assumptions!$B$21 -> 80000000 | L7: =M7/K7 -> 0.16666667 | M7: =O7/N7 -> 13333333 | N7: 3 | O7: =T7*10000000/J7*1000 -> 40000000 | P7: =O7*Assumptions!$B$16 -> 320000 | Q7: =P7/O7 -> 0.008 | T7: 0.2 | U7: Cheap reach
A8: Instagram | B8: Consideration | C8: Think | D8: Performance | E8: Mobile | F8: Site visitors + add-to-cart | G8: Top metros + Tier-2 | H8: Image / collection | I8: CPC | J8: 12 | K8: =Assumptions!$B$21 -> 80000000 | L8: =M8/K8 -> 0.14467593 | M8: =O8/N8 -> 11574074 | N8: 3 | O8: =P8/Assumptions!$B$17 -> 34722222 | P8: =T8*10000000/J8 -> 416666.67 | Q8: =P8/O8 -> 0.012 | T8: 0.5 | U8: Warm early interest
A9: Google Search | B9: Conversion | C9: Do | D9: Performance | E9: All | F9: Brand + category keywords | G9: Top metros + Tier-2 | H9: Search + Shopping | I9: CPC | J9: 25 | K9: =Assumptions!$B$21 -> 80000000 | L9: =M9/K9 -> 0.0625 | M9: =O9/N9 -> 5000000 | N9: 2 | O9: =P9/Assumptions!$B$17 -> 10000000 | P9: =T9*10000000/J9 -> 120000 | Q9: =P9/O9 -> 0.012 | T9: 0.3 | U9: Capture existing demand
A10: Digital subtotal | T10: =SUM(T5:T9) -> 1.8
A12: QUARTER TOTAL (digital + influencer + OOH + store) | B12: 1.8 | C12: Rs Cr

Sheet Q2
A1: COMET media plan · Q2 (Jul-Sep)
K3: Estimated
A4: Platform | B4: Campaign objective | C4: AIDA | D4: Type | E4: Device | F4: Targeting | G4: Geo | H4: Ad format | I4: Buy type | J4: Net rate (Rs) | K4: Audience / search vol | L4: Reach % (SOI) | M4: Est. reach | N4: Avg freq | O4: Est. impressions | P4: Est. clicks | Q4: Est. CTR | R4: Est. views | S4: Est. VTR | T4: Net cost (Rs Cr) | U4: Rationale
A5: State of the Younion + PR | B5: Awareness | C5: See | D5: Branding | E5: All | F5: 18-30 M/F, interest + LAL | G5: National | H5: Native + earned PR | I5: Flat | J5: - | T5: 0.5 | U5: Earn the conversation
A6: Brand film | B6: Awareness | C6: See | D6: Branding | E6: All | F6: 18-30 M/F, interest + LAL | G6: National | H6: Hero film | I6: Flat | J6: - | T6: 1 | U6: The Real Flex hero
A7: YouTube | B7: Awareness | C7: See | D7: Branding | E7: Mobile | F7: 18-30 M/F, interest + LAL | G7: Top metros + Tier-2 | H7: In-stream + Shorts | I7: CPV | J7: 1 | K7: =Assumptions!$B$21 -> 80000000 | L7: =M7/K7 -> 0.13888889 | M7: =O7/N7 -> 11111111 | N7: 3 | O7: =R7/Assumptions!$B$18 -> 33333333 | P7: =O7*Assumptions!$B$16 -> 266666.67 | Q7: =P7/O7 -> 0.008 | R7: =T7*10000000/J7 -> 10000000 | S7: =R7/O7 -> 0.3 | T7: 1 | U7: Amplify the film
A8: Meta / Instagram | B8: Awareness | C8: See | D8: Branding | E8: Mobile | F8: 18-30 M/F, interest + LAL | G8: Top metros + Tier-2 | H8: Reels / Stories | I8: CPM | J8: 80 | K8: =Assumptions!$B$21 -> 80000000 | L8: =M8/K8 -> 0.3125 | M8: =O8/N8 -> 25000000 | N8: 3 | O8: =T8*10000000/J8*1000 -> 75000000 | P8: =O8*Assumptions!$B$16 -> 600000 | Q8: =P8/O8 -> 0.008 | T8: 0.6 | U8: Amplify report + film
A9: Google Display | B9: Awareness | C9: See | D9: Branding | E9: Mobile | F9: 18-30 M/F, interest + LAL | G9: Top metros + Tier-2 | H9: Responsive display | I9: CPM | J9: 50 | K9: =Assumptions!$B$21 -> 80000000 | L9: =M9/K9 -> 0.33333333 | M9: =O9/N9 -> 26666667 | N9: 3 | O9: =T9*10000000/J9*1000 -> 80000000 | P9: =O9*Assumptions!$B$16 -> 640000 | Q9: =P9/O9 -> 0.008 | T9: 0.4 | U9: Sustain reach
A10: Sessions + content | B10: Consideration | C10: Think | D10: Performance | E10: Mobile | F10: 18-30 M/F, interest + LAL | G10: Top metros + Tier-2 | H10: Long-form video | I10: Flat | J10: - | T10: 0.5 | U10: Hub content
A11: Instagram | B11: Consideration | C11: Think | D11: Performance | E11: Mobile | F11: Site visitors + add-to-cart | G11: Top metros + Tier-2 | H11: Image / collection | I11: CPC | J11: 12 | K11: =Assumptions!$B$21 -> 80000000 | L11: =M11/K11 -> 0.2025463 | M11: =O11/N11 -> 16203704 | N11: 3 | O11: =P11/Assumptions!$B$17 -> 48611111 | P11: =T11*10000000/J11 -> 583333.33 | Q11: =P11/O11 -> 0.012 | T11: 0.7 | U11: Drive submissions + waitlist
A12: Meta retargeting | B12: Consideration | C12: Think | D12: Performance | E12: Mobile | F12: Site visitors + add-to-cart | G12: Top metros + Tier-2 | H12: DPA carousel | I12: CPC | J12: 12 | K12: =Assumptions!$B$21 -> 80000000 | L12: =M12/K12 -> 0.10850694 | M12: =O12/N12 -> 8680555.6 | N12: 4 | O12: =P12/Assumptions!$B$17 -> 34722222 | P12: =T12*10000000/J12 -> 416666.67 | Q12: =P12/O12 -> 0.012 | T12: 0.5 | U12: Re-engage viewers
A13: Google Search + Shopping | B13: Conversion | C13: Do | D13: Performance | E13: All | F13: Brand + category keywords | G13: Top metros + Tier-2 | H13: Search + PLA | I13: CPC | J13: 25 | K13: =Assumptions!$B$21 -> 80000000 | L13: =M13/K13 -> 0.20833333 | M13: =O13/N13 -> 16666667 | N13: 2 | O13: =P13/Assumptions!$B$17 -> 33333333 | P13: =T13*10000000/J13 -> 400000 | Q13: =P13/O13 -> 0.012 | T13: 1 | U13: Apex launch intent
A14: Meta / IG conversion + DPA | B14: Conversion | C14: Do | D14: Performance | E14: Mobile | F14: Site visitors + add-to-cart | G14: Top metros + Tier-2 | H14: DPA / collection | I14: CPC | J14: 12 | K14: =Assumptions!$B$21 -> 80000000 | L14: =M14/K14 -> 0.21701389 | M14: =O14/N14 -> 17361111 | N14: 4 | O14: =P14/Assumptions!$B$17 -> 69444444 | P14: =T14*10000000/J14 -> 833333.33 | Q14: =P14/O14 -> 0.012 | T14: 1 | U14: Convert + retarget
A15: Myntra | B15: Conversion | C15: Do | D15: Performance | E15: Mobile | F15: 18-30 M/F, interest + LAL | G15: Top metros + Tier-2 | H15: Banner + PLA | I15: CPM | J15: 150 | K15: =Assumptions!$B$21 -> 80000000 | L15: =M15/K15 -> 0.13888889 | M15: =O15/N15 -> 11111111 | N15: 3 | O15: =T15*10000000/J15*1000 -> 33333333 | P15: =O15*Assumptions!$B$19 -> 333333.33 | Q15: =P15/O15 -> 0.01 | T15: 0.5 | U15: Marketplace
A16: CRM / email | B16: Loyalty | C16: Care | D16: Retention | E16: All | F16: Waitlist | G16: - | H16: Email | I16: Flat | J16: - | T16: 0.3 | U16: Nurture waitlist
A17: Digital subtotal | T17: =SUM(T5:T16) -> 8
A20: Influencer marketing (direct partnerships)
A21: Tier | B21: Example creators / handles | C21: Platform | D21: Deliverables | E21: # creators | F21: Est. reach | G21: Rate / creator (Rs) | H21: Net cost (Rs)
A22: Mid-tier (100k-1M) | B22: Karan Khatri, Suhana Sethi + relatable fashion | C22: IG / YouTube | D22: 2 Reels each | E22: 12 | F22: 1800000 | G22: 250000 | H22: =E22*G22 -> 3000000
A23: Micro (10-100k) | B23: Fashion + sneaker micro pool | C23: Instagram | D23: 1 Reel + 2 Stories | E23: 60 | F23: 1200000 | G23: 40000 | H23: =E23*G23 -> 2400000
A24: Nano / UGC (1-10k) | B24: Campus + sneakerhead nano | C24: Instagram | D24: 1 Reel | E24: 260 | F24: 1040000 | G24: 10000 | H24: =E24*G24 -> 2600000
A25: Influencer subtotal (Rs) | H25: =SUM(H22:H24) -> 8000000
A28: Out-of-home (this quarter)
A29: Market | B29: Location | C29: Format | D29: Dimension | E29: Slots/day | F29: Days | G29: Rate/slot (Rs) | H29: Cost (Rs)
A30: Mumbai | B30: BKC premium screen | C30: Anamorphic 3D DOOH | D30: 20x12 ft | E30: 60 | F30: 21 | G30: 6000 | H30: =E30*F30*G30 -> 7560000
A31: Mumbai | B31: CGI artist commission | C31: Anamorphic creative (one-off) | D31: - | H31: 2440000
A32: OOH subtotal (Rs) | H32: =SUM(H30:H31) -> 10000000
A34: QUARTER TOTAL (digital + influencer + OOH + store) | B34: 9.8 | C34: Rs Cr

Sheet Q3
A1: COMET media plan · Q3 (Oct-Dec, festive peak)
K3: Estimated
A4: Platform | B4: Campaign objective | C4: AIDA | D4: Type | E4: Device | F4: Targeting | G4: Geo | H4: Ad format | I4: Buy type | J4: Net rate (Rs) | K4: Audience / search vol | L4: Reach % (SOI) | M4: Est. reach | N4: Avg freq | O4: Est. impressions | P4: Est. clicks | Q4: Est. CTR | R4: Est. views | S4: Est. VTR | T4: Net cost (Rs Cr) | U4: Rationale
A5: YouTube | B5: Awareness | C5: See | D5: Branding | E5: Mobile | F5: 18-30 M/F, interest + LAL | G5: Top metros + Tier-2 | H5: In-stream + Shorts | I5: CPV | J5: 1 | K5: =Assumptions!$B$21 -> 80000000 | L5: =M5/K5 -> 0.18055556 | M5: =O5/N5 -> 14444444 | N5: 3 | O5: =R5/Assumptions!$B$18 -> 43333333 | P5: =O5*Assumptions!$B$16 -> 346666.67 | Q5: =P5/O5 -> 0.008 | R5: =T5*10000000/J5 -> 13000000 | S5: =R5/O5 -> 0.3 | T5: 1.3 | U5: Festive reach
A6: Meta / Instagram | B6: Awareness | C6: See | D6: Branding | E6: Mobile | F6: 18-30 M/F, interest + LAL | G6: Top metros + Tier-2 | H6: Reels / Stories | I6: CPM | J6: 80 | K6: =Assumptions!$B$21 -> 80000000 | L6: =M6/K6 -> 0.41666667 | M6: =O6/N6 -> 33333333 | N6: 3 | O6: =T6*10000000/J6*1000 -> 100000000 | P6: =O6*Assumptions!$B$16 -> 800000 | Q6: =P6/O6 -> 0.008 | T6: 0.8 | U6: Festive reach
A7: OTT (JioHotstar) | B7: Awareness | C7: See | D7: Branding | E7: CTV + mobile | F7: 18-30 M/F, interest + LAL | G7: Top metros + Tier-2 | H7: Non-skippable pre-roll | I7: CPM | J7: 250 | K7: =Assumptions!$B$21 -> 80000000 | L7: =M7/K7 -> 0.1 | M7: =O7/N7 -> 8000000 | N7: 3 | O7: =T7*10000000/J7*1000 -> 24000000 | P7: =O7*Assumptions!$B$16 -> 192000 | Q7: =P7/O7 -> 0.008 | T7: 0.6 | U7: Premium festive video
A8: Sessions + content | B8: Consideration | C8: Think | D8: Performance | E8: Mobile | F8: 18-30 M/F, interest + LAL | G8: Top metros + Tier-2 | H8: Long-form video | I8: Flat | J8: - | T8: 0.7 | U8: Hub content
A9: Instagram | B9: Consideration | C9: Think | D9: Performance | E9: Mobile | F9: Site visitors + add-to-cart | G9: Top metros + Tier-2 | H9: Image / collection | I9: CPC | J9: 12 | K9: =Assumptions!$B$21 -> 80000000 | L9: =M9/K9 -> 0.23148148 | M9: =O9/N9 -> 18518519 | N9: 3 | O9: =P9/Assumptions!$B$17 -> 55555556 | P9: =T9*10000000/J9 -> 666666.67 | Q9: =P9/O9 -> 0.012 | T9: 0.8 | U9: Push to peak
A10: Meta retargeting | B10: Consideration | C10: Think | D10: Performance | E10: Mobile | F10: Site visitors + add-to-cart | G10: Top metros + Tier-2 | H10: DPA carousel | I10: CPC | J10: 12 | K10: =Assumptions!$B$21 -> 80000000 | L10: =M10/K10 -> 0.15190972 | M10: =O10/N10 -> 12152778 | N10: 4 | O10: =P10/Assumptions!$B$17 -> 48611111 | P10: =T10*10000000/J10 -> 583333.33 | Q10: =P10/O10 -> 0.012 | T10: 0.7 | U10: Re-engage hunt
A11: Google Search + Shopping | B11: Conversion | C11: Do | D11: Performance | E11: All | F11: Brand + category keywords | G11: Top metros + Tier-2 | H11: Search + PLA | I11: CPC | J11: 25 | K11: =Assumptions!$B$21 -> 80000000 | L11: =M11/K11 -> 0.5625 | M11: =O11/N11 -> 45000000 | N11: 2 | O11: =P11/Assumptions!$B$17 -> 90000000 | P11: =T11*10000000/J11 -> 1080000 | Q11: =P11/O11 -> 0.012 | T11: 2.7 | U11: Festive capture
A12: Meta / IG conversion + DPA | B12: Conversion | C12: Do | D12: Performance | E12: Mobile | F12: Site visitors + add-to-cart | G12: Top metros + Tier-2 | H12: DPA / collection | I12: CPC | J12: 12 | K12: =Assumptions!$B$21 -> 80000000 | L12: =M12/K12 -> 0.5859375 | M12: =O12/N12 -> 46875000 | N12: 4 | O12: =P12/Assumptions!$B$17 -> 187500000 | P12: =T12*10000000/J12 -> 2250000 | Q12: =P12/O12 -> 0.012 | T12: 2.7 | U12: Peak conversion
A13: Myntra | B13: Conversion | C13: Do | D13: Performance | E13: Mobile | F13: 18-30 M/F, interest + LAL | G13: Top metros + Tier-2 | H13: Banner + PLA | I13: CPM | J13: 150 | K13: =Assumptions!$B$21 -> 80000000 | L13: =M13/K13 -> 0.44444444 | M13: =O13/N13 -> 35555556 | N13: 3 | O13: =T13*10000000/J13*1000 -> 1.0666667e+08 | P13: =O13*Assumptions!$B$19 -> 1066666.7 | Q13: =P13/O13 -> 0.01 | T13: 1.6 | U13: Big Fashion Festival
A14: Parties / events | B14: Conversion | C14: Do | D14: Performance | E14: On-ground | F14: Apex buyers + scene | G14: Mum/Blr/NCR | H14: Experiential + kiosk | I14: Flat | J14: - | T14: 1.7 | U14: The Moment
A15: Chip sessions (Boiler Room) | B15: Loyalty | C15: Care | D15: Retention | E15: On-ground | F15: Chip holders | G15: Party cities | H15: Experiential + video | I15: Flat | J15: - | T15: 0.5 | U15: Loyalty ritual
A16: CRM / email | B16: Loyalty | C16: Care | D16: Retention | E16: All | F16: Buyers | G16: - | H16: Email | I16: Flat | J16: - | T16: 0.6 | U16: Lifecycle
A17: Digital subtotal | T17: =SUM(T5:T16) -> 14.7
A20: Influencer marketing (direct partnerships)
A21: Tier | B21: Example creators / handles | C21: Platform | D21: Deliverables | E21: # creators | F21: Est. reach | G21: Rate / creator (Rs) | H21: Net cost (Rs)
A22: Mid-tier (100k-1M) | B22: Karan Khatri, sneakerpreacher.in, Suhana Sethi + relatable | C22: IG / YouTube | D22: 2 Reels each | E22: 16 | F22: 2400000 | G22: 250000 | H22: =E22*G22 -> 4000000
A23: Micro (10-100k) | B23: Fashion + sneaker micro pool | C23: Instagram | D23: 1 Reel + 2 Stories | E23: 80 | F23: 1600000 | G23: 40000 | H23: =E23*G23 -> 3200000
A24: Nano / UGC (1-10k) | B24: Campus + party UGC | C24: Instagram | D24: 1 Reel | E24: 280 | F24: 1120000 | G24: 10000 | H24: =E24*G24 -> 2800000
A25: Influencer subtotal (Rs) | H25: =SUM(H22:H24) -> 10000000
A28: Out-of-home (this quarter)
A29: Market | B29: Location | C29: Format | D29: Dimension | E29: Slots/day | F29: Days | G29: Rate/slot (Rs) | H29: Cost (Rs)
A30: Mumbai | B30: Bandra wall | C30: Permitted mural + QR cipher | D30: Large wall | H30: 600000
A31: Mumbai | B31: Andheri wall | C31: Permitted mural + QR cipher | D31: Large wall | H31: 600000
A32: Mumbai | B32: Lower Parel wall | C32: Permitted mural + QR cipher | D32: Large wall | H32: 600000
A33: Bengaluru | B33: Indiranagar wall | C33: Permitted mural + QR cipher | D33: Large wall | H33: 550000
A34: Bengaluru | B34: Koramangala wall | C34: Permitted mural + QR cipher | D34: Large wall | H34: 550000
A35: Bengaluru | B35: HSR wall | C35: Permitted mural + QR cipher | D35: Large wall | H35: 550000
A36: Delhi NCR | B36: Hauz Khas wall | C36: Permitted mural + QR cipher | D36: Large wall | H36: 500000
A37: Delhi NCR | B37: GK wall | C37: Permitted mural + QR cipher | D37: Large wall | H37: 500000
A38: Delhi NCR | B38: Gurgaon wall | C38: Permitted mural + QR cipher | D38: Large wall | H38: 550000
A39: OOH subtotal (Rs) | H39: =SUM(H30:H38) -> 5000000
A41: QUARTER TOTAL (digital + influencer + OOH + store) | B41: 16.2 | C41: Rs Cr

Sheet Q4
A1: COMET media plan · Q4 (Jan-Mar)
K3: Estimated
A4: Platform | B4: Campaign objective | C4: AIDA | D4: Type | E4: Device | F4: Targeting | G4: Geo | H4: Ad format | I4: Buy type | J4: Net rate (Rs) | K4: Audience / search vol | L4: Reach % (SOI) | M4: Est. reach | N4: Avg freq | O4: Est. impressions | P4: Est. clicks | Q4: Est. CTR | R4: Est. views | S4: Est. VTR | T4: Net cost (Rs Cr) | U4: Rationale
A5: YouTube | B5: Awareness | C5: See | D5: Branding | E5: Mobile | F5: 18-30 M/F, interest + LAL | G5: Top metros + Tier-2 | H5: In-stream + Shorts | I5: CPV | J5: 1 | K5: =Assumptions!$B$21 -> 80000000 | L5: =M5/K5 -> 0.069444444 | M5: =O5/N5 -> 5555555.6 | N5: 3 | O5: =R5/Assumptions!$B$18 -> 16666667 | P5: =O5*Assumptions!$B$16 -> 133333.33 | Q5: =P5/O5 -> 0.008 | R5: =T5*10000000/J5 -> 5000000 | S5: =R5/O5 -> 0.3 | T5: 0.5 | U5: Sustain reach
A6: Meta / Instagram | B6: Awareness | C6: See | D6: Branding | E6: Mobile | F6: 18-30 M/F, interest + LAL | G6: Top metros + Tier-2 | H6: Reels / Stories | I6: CPM | J6: 80 | K6: =Assumptions!$B$21 -> 80000000 | L6: =M6/K6 -> 0.15625 | M6: =O6/N6 -> 12500000 | N6: 3 | O6: =T6*10000000/J6*1000 -> 37500000 | P6: =O6*Assumptions!$B$16 -> 300000 | Q6: =P6/O6 -> 0.008 | T6: 0.3 | U6: Sustain
A7: Sessions + content | B7: Consideration | C7: Think | D7: Performance | E7: Mobile | F7: 18-30 M/F, interest + LAL | G7: Top metros + Tier-2 | H7: Long-form video | I7: Flat | J7: - | T7: 0.3 | U7: Hub content
A8: Instagram | B8: Consideration | C8: Think | D8: Performance | E8: Mobile | F8: Site visitors + add-to-cart | G8: Top metros + Tier-2 | H8: Image / collection | I8: CPC | J8: 12 | K8: =Assumptions!$B$21 -> 80000000 | L8: =M8/K8 -> 0.086805556 | M8: =O8/N8 -> 6944444.4 | N8: 3 | O8: =P8/Assumptions!$B$17 -> 20833333 | P8: =T8*10000000/J8 -> 250000 | Q8: =P8/O8 -> 0.012 | T8: 0.3 | U8: Sustain interest
A9: Google Search + Shopping | B9: Conversion | C9: Do | D9: Performance | E9: All | F9: Brand + category keywords | G9: Top metros + Tier-2 | H9: Search + PLA | I9: CPC | J9: 25 | K9: =Assumptions!$B$21 -> 80000000 | L9: =M9/K9 -> 0.20833333 | M9: =O9/N9 -> 16666667 | N9: 2 | O9: =P9/Assumptions!$B$17 -> 33333333 | P9: =T9*10000000/J9 -> 400000 | Q9: =P9/O9 -> 0.012 | T9: 1 | U9: EOSS / winter capture
A10: Meta / IG conversion + DPA | B10: Conversion | C10: Do | D10: Performance | E10: Mobile | F10: Site visitors + add-to-cart | G10: Top metros + Tier-2 | H10: DPA / collection | I10: CPC | J10: 12 | K10: =Assumptions!$B$21 -> 80000000 | L10: =M10/K10 -> 0.17361111 | M10: =O10/N10 -> 13888889 | N10: 4 | O10: =P10/Assumptions!$B$17 -> 55555556 | P10: =T10*10000000/J10 -> 666666.67 | Q10: =P10/O10 -> 0.012 | T10: 0.8 | U10: Convert winter demand
A11: Myntra | B11: Conversion | C11: Do | D11: Performance | E11: Mobile | F11: 18-30 M/F, interest + LAL | G11: Top metros + Tier-2 | H11: Banner + PLA | I11: CPM | J11: 150 | K11: =Assumptions!$B$21 -> 80000000 | L11: =M11/K11 -> 0.11111111 | M11: =O11/N11 -> 8888888.9 | N11: 3 | O11: =T11*10000000/J11*1000 -> 26666667 | P11: =O11*Assumptions!$B$19 -> 266666.67 | Q11: =P11/O11 -> 0.01 | T11: 0.4 | U11: Marketplace
A12: Parties / events (tail) | B12: Conversion | C12: Do | D12: Performance | E12: On-ground | F12: Scene | G12: Metros | H12: Experiential | I12: Flat | J12: - | T12: 0.3 | U12: Year-end spike
A13: Chip sessions (Boiler Room) | B13: Loyalty | C13: Care | D13: Retention | E13: On-ground | F13: Chip holders | G13: Metros | H13: Experiential + video | I13: Flat | J13: - | T13: 1 | U13: Ongoing loyalty
A14: CRM / email | B14: Loyalty | C14: Care | D14: Retention | E14: All | F14: Buyers | G14: - | H14: Email | I14: Flat | J14: - | T14: 0.6 | U14: Retention
A15: Digital subtotal | T15: =SUM(T5:T14) -> 5.5
A18: Influencer marketing (direct partnerships)
A19: Tier | B19: Example creators / handles | C19: Platform | D19: Deliverables | E19: # creators | F19: Est. reach | G19: Rate / creator (Rs) | H19: Net cost (Rs)
A20: Mid-tier (100k-1M) | B20: Relatable fashion + sneaker | C20: IG | D20: 1 Reel | E20: 2 | F20: 300000 | G20: 250000 | H20: =E20*G20 -> 500000
A21: Micro (10-100k) | B21: Fashion + sneaker micro pool | C21: Instagram | D21: 1 Reel | E21: 20 | F21: 400000 | G21: 40000 | H21: =E21*G21 -> 800000
A22: Nano / UGC (1-10k) | B22: Testimonial + UGC | C22: Instagram | D22: 1 Reel / Story | E22: 70 | F22: 350000 | G22: 10000 | H22: =E22*G22 -> 700000
A23: Influencer subtotal (Rs) | H23: =SUM(H20:H22) -> 2000000
A26: Out-of-home (this quarter)
A27: Market | B27: Location | C27: Format | D27: Dimension | E27: Slots/day | F27: Days | G27: Rate/slot (Rs) | H27: Cost (Rs)
A28: Ahmedabad | B28: Flagship precinct | C28: Street-art exhibition (install) | D28: Multi-wall | H28: 7000000
A29: Ahmedabad | B29: Public venue | C29: Exhibition production + events | D29: Venue | H29: 3000000
A30: OOH subtotal (Rs) | H30: =SUM(H28:H29) -> 10000000
A33: Q4 store-visit campaign · Google Performance Max (footfall)
A34: Separate table: success metric is store footfall, not clicks (the PMax rule). Drives the Ahmedabad flagship + metro stores.
A35: Platform | B35: Objective | C35: Device | D35: Targeting | E35: Ad format | F35: Buy type | G35: Net rate (Rs) | H35: Est. impressions | I35: Est. clicks | J35: Est. CTR | K35: Est. footfall | L35: Footfall rate | M35: Cost / footfall (Rs) | N35: Net cost (Rs Cr)
A36: Google PMax | B36: Store footfall | C36: All | D36: 5km radius of stores (Ahmedabad + metros) | E36: Display + Search | F36: CPC | G36: 14 | H36: =I36/Assumptions!$B$17 -> 29761905 | I36: =N36*10000000/G36 -> 357142.86 | J36: =I36/H36 -> 0.012 | K36: =I36*Assumptions!$B$20 -> 14285.714 | L36: =Assumptions!$B$20 -> 0.04 | M36: =N36*10000000/K36 -> 350 | N36: 0.5
A38: QUARTER TOTAL (digital + influencer + OOH + store) | B38: 7.2 | C38: Rs Cr

Sheet Budget
A1: Budget by funnel stage (Rs Cr, net media; master reconciliation)
A3: Platform / asset | B3: Buy type | C3: Q1 | D3: Q2 | E3: Q3 | F3: Q4 | G3: Total
A4: SEE - awareness
A5: State of the Younion + PR | B5: Flat | C5: - | D5: 0.5 | E5: - | F5: - | G5: =SUM(C5:F5) -> 0.5
A6: Brand film | B6: Flat | C6: - | D6: 1 | E6: - | F6: - | G6: =SUM(C6:F6) -> 1
A7: OOH (anamorphic, graffiti, Ahmedabad expo) | B7: Flat/CPD | C7: - | D7: 1 | E7: 0.5 | F7: 1 | G7: =SUM(C7:F7) -> 2.5
A8: Reach media (YouTube/Meta/OTT/GDN) | B8: CPV/CPM | C8: 1 | D8: 2 | E8: 2.7 | F8: 0.8 | G8: =SUM(C8:F8) -> 6.5
A9: THINK - consideration
A10: Sessions + content | B10: Flat | C10: - | D10: 0.5 | E10: 0.7 | F10: 0.3 | G10: =SUM(C10:F10) -> 1.5
A11: Influencer (direct partnerships) | B11: Flat/CPM | C11: - | D11: 0.8 | E11: 1 | F11: 0.2 | G11: =SUM(C11:F11) -> 2
A12: Consideration + retargeting | B12: CPC | C12: 0.5 | D12: 1.2 | E12: 1.5 | F12: 0.3 | G12: =SUM(C12:F12) -> 3.5
A13: DO - conversion
A14: Search + Shopping / PMax | B14: CPC | C14: 0.3 | D14: 1 | E14: 2.7 | F14: 1 | G14: =SUM(C14:F14) -> 5
A15: Meta/IG conversion + DPA | B15: CPC | C15: - | D15: 1 | E15: 2.7 | F15: 0.8 | G15: =SUM(C15:F15) -> 4.5
A16: Myntra + marketplace | B16: CPC/CPM | C16: - | D16: 0.5 | E16: 1.6 | F16: 0.4 | G16: =SUM(C16:F16) -> 2.5
A17: Parties / events | B17: Flat | C17: - | D17: - | E17: 1.7 | F17: 0.3 | G17: =SUM(C17:F17) -> 2
A18: PMax store-visit (footfall) | B18: CPC | C18: - | D18: - | E18: - | F18: 0.5 | G18: =SUM(C18:F18) -> 0.5
A19: CARE - loyalty
A20: Chip sessions + Boiler Room | B20: Flat | C20: - | D20: - | E20: 0.5 | F20: 1 | G20: =SUM(C20:F20) -> 1.5
A21: CRM / email + lifecycle | B21: CPM | C21: - | D21: 0.3 | E21: 0.6 | F21: 0.6 | G21: =SUM(C21:F21) -> 1.5
A22: Quarter totals | C22: =SUM(C5,C6,C7,C8,C10,C11,C12,C14,C15,C16,C17,C18,C20,C21) -> 1.8 | D22: =SUM(D5,D6,D7,D8,D10,D11,D12,D14,D15,D16,D17,D18,D20,D21) -> 9.8 | E22: =SUM(E5,E6,E7,E8,E10,E11,E12,E14,E15,E16,E17,E18,E20,E21) -> 16.2 | F22: =SUM(F5,F6,F7,F8,F10,F11,F12,F14,F15,F16,F17,F18,F20,F21) -> 7.2 | G22: =SUM(G5,G6,G7,G8,G10,G11,G12,G14,G15,G16,G17,G18,G20,G21) -> 35

Sheet Flighting
A1: Flighting - spend weight by month (darker = more)
A3: Channel | B3: Apr | C3: May | D3: Jun | E3: Jul | F3: Aug | G3: Sep | H3: Oct | I3: Nov | J3: Dec | K3: Jan | L3: Feb | M3: Mar
A4: Google Search
A5: Instagram / Meta
A6: YouTube
A7: OTT (JioHotstar)
A8: Influencers
A9: OOH / graffiti / expo
A10: Report / PR
A11: Parties / events
A12: Sessions (Boiler Room)
A13: Email / CRM
A15: Sep-Oct = the 6-week burst; festive harvest holds Search/Meta/OTT high to January.

Sheet Content Calendar
A1: Content calendar - Hero / Hub / Hygiene, locked to the media weeks
A3: Window | B3: Funnel | C3: Content piece | D3: Format | E3: Channels | F3: PESO | G3: Persona | H3: KPI
A4: Jul-Aug | B4: See | C4: State of the Younion report | D4: Hero | E4: PR, site, LinkedIn | F4: Earned/Owned | G4: Rohan | H4: Media pickups
A5: Jul-Aug | B5: See | C5: Teaser stats drip | D5: Hub | E5: IG, X | F5: Shared | G5: All | H5: Share of search
A6: Sep | B6: See | C6: The Real Flex brand film | D6: Hero | E6: YouTube, OTT, Meta | F6: Paid/Owned | G6: All | H6: Views, brand lift
A7: Sep | B7: See | C7: Anamorphic OOH film | D7: Hero | E7: OOH, social | F7: Earned/Paid | G7: Sneha, Arjun | H7: Earned reach
A8: Sep-Oct | B8: Think | C8: Graffiti cipher hunt | D8: Hub | E8: OOH, IG, microsite | F8: Earned/Shared | G8: Arjun | H8: Scans, emails
A9: Sep-Oct | B9: Think | C9: Creator real-vs-posted | D9: Hub | E9: IG, YouTube | F9: Shared/Paid | G9: Sneha | H9: Submissions
A10: Sep-Oct | B10: Think | C10: Apex design story | D10: Hub | E10: IG, YouTube, site | F10: Owned | G10: Sneha | H10: Waitlist
A11: Sep-Jan | B11: Do | C11: Apex demos + AI fit-finder | D11: Hygiene | E11: Site, Search | F11: Owned/Paid | G11: Sneha | H11: Conversion rate
A12: Sep-Jan | B12: Do | C12: Search + DPA retargeting | D12: Hygiene | E12: Search, Meta, Myntra | F12: Paid | G12: Sneha | H12: ROAS, CAC
A13: Oct-Nov | B13: Do | C13: Underground party films | D13: Hero | E13: YouTube, IG, PR | F13: Earned/Owned | G13: All | H13: UGC reach
A14: Oct-Mar | B14: Care | C14: Recorded sessions / tracks | D14: Hub | E14: YouTube, Spotify | F14: Owned/Shared | G14: Arjun, Rohan | H14: Subs
... A16: Oct-Mar | B16: Care | C16: CRM / lifecycle flows | D16: Hygiene | E16: Email | F16: Owned | G16: All | H16: Repeat, LTV
